{"index.md":"DpIt_iQ0","src__cli-md_cli-run.md":"B1sVpfLV","src__cli-md_cli-storybook-react.md":"DDVoK_kX","src__cli-md_cli-storybook-vue.md":"D8CGdPSq","src__components-md_packages-components.md":"YWMVIklY","src__conf-md_packages-conf.md":"C-ttRIOc","src__css-md_packages-style.md":"DS0XJUpS","src__dev-md_eslint-config.md":"CtlSOqD4","src__dev-md_prettier-config.md":"DnSjF10v","src__dev-md_stylelint-config.md":"BIJimexE","src__dev-md_ts-config.md":"q7UuioQ_","src__fetch-md_request-axios.md":"Bjr7xUEG","src__react-md_react-ant-design-extra.md":"h2IU0sa8","src__react-md_react-hooks.md":"c80kG1FQ","src__ts-md_packages-enum.md":"Cxb6FmmT","src__ts-md_packages-types.md":"C7fMgZ6s","src__utils-md_packages-utils.md":"QmReOcVT","src__vite-md_packages-vite-plugins.md":"ChGi9ToK","src__vue-md_vue-components.md":"aAMnsqrx","src__vue-md_vue-config.md":"CUdxWxHS","src__vue-md_vue-directives.md":"CEPGaByz","src__vue-md_vue-echarts.md":"Dt-KSWlg","src__vue-md_vue-element-plus-extra.md":"DvydixBs","src__vue-md_vue-hooks.md":"BMgewXhk"}
