{"index.md":"DhZf593I","src__components-md_packages-components.md":"DsSeK955","src__conf-md_packages-conf.md":"sk2xbkCO","src__css-md_packages-style.md":"BNTCOfdg","src__dev-md_eslint-config.md":"D08UxdkZ","src__dev-md_prettier-config.md":"C6v8IkvJ","src__dev-md_stylelint-config.md":"DLH_14IQ","src__dev-md_ts-config.md":"DBCsSiCZ","src__ts-md_packages-enum.md":"C2CsJFxh","src__ts-md_packages-types.md":"DNVZIfRq","src__utils-md_packages-utils.md":"QWJ4NjV_","src__vite-md_packages-vite-plugins.md":"6FgRwrje"}
